pillow_tools/__init__.py
pillow_tools-1.1.2.dist-info/METADATA
pillow_tools-1.1.2.dist-info/WHEEL
pillow_tools-1.1.2.dist-info/top_level.txt
pillow_tools-1.1.2.dist-info/RECORD
